lexref/__init__.py
lexref/celex_handling.py
lexref/reflector.py
lexref/settings.py
lexref/structures.py
lexref/token_sequences.py
lexref/utils.py
lexref/model/__init__.py
lexref/model/group.py
lexref/model/tables.py
lexref/static/named_entity.csv
lexref-1.1.dist-info/LICENSE
lexref-1.1.dist-info/METADATA
lexref-1.1.dist-info/WHEEL
lexref-1.1.dist-info/top_level.txt
lexref-1.1.dist-info/RECORD
