Metadata-Version: 2.1
Name: lexref
Version: 1.1
Summary: LEgislative teXt REFerence extraction
Home-page: https://github.com/Lexparency/lexref
Author: Martin Heimsoth
Author-email: mail@lexparency.org
License: UNKNOWN
Platform: UNKNOWN
License-File: LICENSE
Requires-Dist: anytree
Requires-Dist: lxml
